Users/Anish/.escat/config.yml
escat/__init__.py
escat/api.py
escat/config.py
escat/main.py
escat/utils.py
escat/tests/__init__.py
escat/tests/tests.py
escat-1.0.0.data/scripts/escat
escat-1.0.0.dist-info/METADATA
escat-1.0.0.dist-info/RECORD
escat-1.0.0.dist-info/WHEEL
escat-1.0.0.dist-info/top_level.txt
