Metadata-Version: 2.1
Name: escat
Version: 1.0.0
Summary: Command line wrapper for Elasticsearch CAT API
Home-page: https://github.com/itisanish/escat
Author: Anish Mashankar
License: UNKNOWN
Platform: UNKNOWN
Classifier: Programming Language :: Python :: 3
Classifier: License :: OSI Approved :: MIT License
Classifier: Operating System :: OS Independent
Requires-Python: >=3.0
Requires-Dist: elasticsearch
Requires-Dist: pyyaml
